Metadata-Version: 2.1
Name: CloudHummingbird
Version: 1.1.0
Summary: A tool that recommends the best way to run your genomics pipelines on the cloud
Home-page: https://github.com/StanfordBioinformatics/Hummingbird
Author: Stanford Center For Genomics And Personalized Medicine
Author-email: abahman@stanford.edu
License: UNKNOWN
Project-URL: Bug Reports, https://github.com/StanfordBioinformatics/Hummingbird/issues
Project-URL: Source, https://github.com/StanfordBioinformatics/Hummingbird
Platform: UNKNOWN
Classifier: Intended Audience :: Science/Research
Classifier: Topic :: Scientific/Engineering :: Bio-Informatics
Classifier: License :: OSI Approved :: Apache Software License
Classifier: Programming Language :: Python :: 3.6
Classifier: Programming Language :: Python :: 3.7
Classifier: Programming Language :: Python :: 3.8
Requires-Python: >=3.6, <4
License-File: LICENSE.txt
Requires-Dist: dsub (==0.3.6)
Requires-Dist: future (==0.18.2)
Requires-Dist: configparser (==5.0.0)
Requires-Dist: scipy (==1.5.2)
Requires-Dist: numpy (==1.19.1)
Requires-Dist: matplotlib (==3.3.0)
Requires-Dist: scikit-learn (==0.23.2)
Requires-Dist: google-cloud-storage (==1.30.0)
Requires-Dist: boto3 (==1.18.6)
Requires-Dist: azure-storage-blob (==12.6.0)
Requires-Dist: azure-identity (==1.5.0)
Requires-Dist: azure-batch (==10.0.0)
Requires-Dist: azure-mgmt-compute (==18.0.0)
Requires-Dist: retry (==0.9.2)
Provides-Extra: tests
Requires-Dist: mock ; extra == 'tests'
